<annotation>
	<folder></folder>
	<filename>WEB-0091_jpg.rf.56224f88db5c12e858ccebfb620c23c9.jpg</filename>
	<path>WEB-0091_jpg.rf.56224f88db5c12e858ccebfb620c23c9.jpg</path>
	<source>
		<database>roboflow.com</database>
	</source>
	<size>
		<width>640</width>
		<height>640</height>
		<depth>3</depth>
	</size>
	<segmented>0</segmented>
	<object>
		<name>Loose bolt</name>
		<pose>Unspecified</pose>
		<truncated>0</truncated>
		<difficult>0</difficult>
		<occluded>0</occluded>
		<bndbox>
			<xmin>195</xmin>
			<xmax>475</xmax>
			<ymin>1</ymin>
			<ymax>459</ymax>
		</bndbox>
	</object>
	<object>
		<name>Regular bolt</name>
		<pose>Unspecified</pose>
		<truncated>0</truncated>
		<difficult>0</difficult>
		<occluded>0</occluded>
		<bndbox>
			<xmin>194</xmin>
			<xmax>470</xmax>
			<ymin>1</ymin>
			<ymax>393</ymax>
		</bndbox>
	</object>
</annotation>
